aioimmich/__init__.py
aioimmich/api.py
aioimmich/const.py
aioimmich/exceptions.py
aioimmich/py.typed
aioimmich/albums/__init__.py
aioimmich/albums/models.py
aioimmich/assets/__init__.py
aioimmich/assets/models.py
aioimmich/people/__init__.py
aioimmich/people/models.py
aioimmich/search/__init__.py
aioimmich/server/__init__.py
aioimmich/server/models.py
aioimmich/tags/__init__.py
aioimmich/tags/models.py
aioimmich/users/__init__.py
aioimmich/users/models.py
aioimmich-0.11.1.dist-info/licenses/LICENSE
aioimmich-0.11.1.dist-info/METADATA
aioimmich-0.11.1.dist-info/WHEEL
aioimmich-0.11.1.dist-info/top_level.txt
aioimmich-0.11.1.dist-info/RECORD
