Metadata-Version: 2.4
Name: aioimmich
Version: 0.11.1
Summary: Asynchronous library to fetch albums and assests from immich.
Author: mib1185
License: Apache-2.0
Project-URL: homepage, https://github.com/mib1185/aioimmich
Project-URL: repository, https://github.com/mib1185/aioimmich
Platform: any
Classifier: Intended Audience :: Developers
Classifier: Operating System :: OS Independent
Classifier: Programming Language :: Python
Classifier: Programming Language :: Python :: 3
Classifier: Programming Language :: Python :: 3.11
Classifier: Programming Language :: Python :: 3.12
Classifier: Programming Language :: Python :: 3.13
Classifier: Topic :: Software Development :: Libraries :: Python Modules
Requires-Python: >=3.11
License-File: LICENSE
Requires-Dist: aiofiles
Requires-Dist: aiohttp
Requires-Dist: mashumaro
Dynamic: license-file
